[{"id":1,"createdAt":946677600000,"model":"model1","maxWeight":100.0,"additionalInformation":null,"climatControlType":null},{"id":4,"createdAt":946677600000,"model":"model4","maxWeight":100.0,"additionalInformation":null,"climatControlType":null},{"id":7,"createdAt":946677600000,"model":"model7","maxWeight":100.0,"additionalInformation":null,"climatControlType":null},{"id":10,"createdAt":946677600000,"model":"model10","maxWeight":100.0,"additionalInformation":null,"climatControlType":null},{"id":13,"createdAt":946677600000,"model":"model13","maxWeight":100.0,"additionalInformation":null,"climatControlType":null},{"id":16,"createdAt":946677600000,"model":"model16","maxWeight":100.0,"additionalInformation":null,"climatControlType":null},{"id":19,"createdAt":946677600000,"model":"model19","maxWeight":100.0,"additionalInformation":null,"climatControlType":null},{"id":2,"createdAt":946677600000,"model":"model2","maxWeight":100.0,"additionalInformation":null,"climatControlType":null},{"id":5,"createdAt":946677600000,"model":"model5","maxWeight":100.0,"additionalInformation":null,"climatControlType":null},{"id":8,"createdAt":946677600000,"model":"model8","maxWeight":100.0,"additionalInformation":null,"climatControlType":null},{"id":11,"createdAt":946677600000,"model":"model11","maxWeight":100.0,"additionalInformation":null,"climatControlType":null},{"id":14,"createdAt":946677600000,"model":"model14","maxWeight":100.0,"additionalInformation":null,"climatControlType":null},{"id":17,"createdAt":946677600000,"model":"model17","maxWeight":100.0,"additionalInformation":null,"climatControlType":null},{"id":20,"createdAt":946677600000,"model":"model20","maxWeight":100.0,"additionalInformation":null,"climatControlType":null},{"id":3,"createdAt":946677600000,"model":"model3","maxWeight":100.0,"additionalInformation":null,"climatControlType":null},{"id":6,"createdAt":946677600000,"model":"model6","maxWeight":100.0,"additionalInformation":null,"climatControlType":null},{"id":9,"createdAt":946677600000,"model":"model9","maxWeight":100.0,"additionalInformation":null,"climatControlType":null},{"id":12,"createdAt":946677600000,"model":"model12","maxWeight":100.0,"additionalInformation":null,"climatControlType":null},{"id":15,"createdAt":946677600000,"model":"model15","maxWeight":100.0,"additionalInformation":null,"climatControlType":null},{"id":18,"createdAt":946677600000,"model":"model18","maxWeight":100.0,"additionalInformation":null,"climatControlType":null}]